insight/__init__.py
insight/ai/__init__.py
insight/ai/adversarial_ae.py
insight/ai/base_gan.py
insight/ai/configuration.py
insight/ai/data_investigation.py
insight/ai/gan.py
insight/ai/gan_configuration.py
insight/ai/least_square_gan.py
insight/ai/metrics.py
insight/ai/net_layers.py
insight/ai/pipeline.py
insight/ai/utils.py
insight/ai/vanilla_gan.py
insight/ai/wgan.py
rivalgan/__init__.py
rivalgan/adversarial_ae.py
rivalgan/base_gan.py
rivalgan/configuration.py
rivalgan/data_investigation.py
rivalgan/gan.py
rivalgan/gan_configuration.py
rivalgan/least_square_gan.py
rivalgan/metrics.py
rivalgan/net_layers.py
rivalgan/pipeline.py
rivalgan/utils.py
rivalgan/vanilla_gan.py
rivalgan/wgan.py
rivalgan-0.4.dist-info/METADATA
rivalgan-0.4.dist-info/RECORD
rivalgan-0.4.dist-info/WHEEL
rivalgan-0.4.dist-info/top_level.txt
