Metadata-Version: 2.1
Name: rivalgan
Version: 0.4
Summary: Generate business data to balance classes
Home-page: https://github.com/InsightDataCommunity/Rival-AI.NY-18C
Author: Yves Greatti
Author-email: yvgrotti@gmail.com
License: UNKNOWN
Platform: UNKNOWN
